{
    "AX":{
        "error":0.0042156773,
        "error_type":"SEM",
        "filter_outliers_dict":{
            "filter_outliers":true,
            "iterations":1,
            "std_devs":2
        },
        "fit":"average",
        "value":0.0009831079
    },
    "CDD":{
        "error":0.0000086026,
        "error_type":"SEM",
        "filter_outliers_dict":{
            "filter_outliers":true,
            "iterations":1,
            "std_devs":10
        },
        "fit":"average",
        "value":0.0000696274
    },
    "H1":{
        "error":0.0029191126,
        "error_type":"SEM",
        "filter_outliers_dict":{
            "filter_outliers":true,
            "iterations":1,
            "std_devs":2
        },
        "fit":"average",
        "value":0.0377321611
    },
    "H2":{
        "error":0.0094654931,
        "error_type":"SEM",
        "filter_outliers_dict":{
            "filter_outliers":true,
            "iterations":1,
            "std_devs":2
        },
        "fit":"average",
        "value":0.0503467045
    },
    "L1":{
        "error":0.0017313392,
        "error_type":"SEM",
        "filter_outliers_dict":{
            "filter_outliers":true,
            "iterations":1,
            "std_devs":2
        },
        "fit":"average",
        "value":-0.0416613791
    },
    "L2":{
        "error":0.0035480049,
        "error_type":"SEM",
        "filter_outliers_dict":{
            "filter_outliers":true,
            "iterations":1,
            "std_devs":2
        },
        "fit":"average",
        "value":-0.0419043761
    }
}