{
    "Ar36":{
        "error":0.0001482164,
        "error_type":"SEM",
        "filter_outliers_dict":{
            "filter_outliers":true,
            "iterations":1,
            "std_devs":2
        },
        "fit":"Linear",
        "value":0.0082926054
    },
    "Ar37":{
        "error":0.0047023367,
        "error_type":"SEM",
        "filter_outliers_dict":{
            "filter_outliers":true,
            "iterations":1,
            "std_devs":2
        },
        "fit":"linear",
        "value":0.0119387442
    },
    "Ar38":{
        "error":0.0024766439,
        "error_type":"SEM",
        "filter_outliers_dict":{
            "filter_outliers":true,
            "iterations":1,
            "std_devs":2
        },
        "fit":"linear",
        "value":0.0283521119
    },
    "Ar39":{
        "error":0.0057494964,
        "error_type":"SEM",
        "filter_outliers_dict":{
            "filter_outliers":true,
            "iterations":1,
            "std_devs":2
        },
        "fit":"Linear",
        "value":4.9585929343
    },
    "Ar40":{
        "error":0.0715751944,
        "error_type":"SEM",
        "filter_outliers_dict":{
            "filter_outliers":true,
            "iterations":1,
            "std_devs":2
        },
        "fit":"Linear",
        "value":1040.665257606
    },
    "Ar41":{
        "error":0.0057484704,
        "error_type":"SEM",
        "filter_outliers_dict":{
            "filter_outliers":true,
            "iterations":1,
            "std_devs":2
        },
        "fit":"Average",
        "value":0.0583274705
    }
}