{
    "Ar36":{
        "error":0.0001080804,
        "error_type":"SEM",
        "filter_outliers_dict":{
            "filter_outliers":true,
            "iterations":1,
            "std_devs":2
        },
        "fit":"Linear",
        "value":0.0058124963
    },
    "Ar37":{
        "error":0.0047840038,
        "error_type":"SEM",
        "filter_outliers_dict":{
            "filter_outliers":true,
            "iterations":1,
            "std_devs":2
        },
        "fit":"linear",
        "value":0.0110447389
    },
    "Ar38":{
        "error":0.0023703124,
        "error_type":"SEM",
        "filter_outliers_dict":{
            "filter_outliers":true,
            "iterations":1,
            "std_devs":2
        },
        "fit":"linear",
        "value":-0.02372006
    },
    "Ar39":{
        "error":0.0059083236,
        "error_type":"SEM",
        "filter_outliers_dict":{
            "filter_outliers":true,
            "iterations":1,
            "std_devs":2
        },
        "fit":"Linear",
        "value":0.8349015982
    },
    "Ar40":{
        "error":0.0163654955,
        "error_type":"SEM",
        "filter_outliers_dict":{
            "filter_outliers":true,
            "iterations":1,
            "std_devs":2
        },
        "fit":"Linear",
        "value":53.5350440162
    },
    "Ar41":{
        "error":0.0057353785,
        "error_type":"SEM",
        "filter_outliers_dict":{
            "filter_outliers":true,
            "iterations":1,
            "std_devs":2
        },
        "fit":"Average",
        "value":0.0291615658
    }
}